cmp_text_files/__init__.py
cmp_text_files/comparison.py
cmp_text_files-0.1.1.dist-info/METADATA
cmp_text_files-0.1.1.dist-info/WHEEL
cmp_text_files-0.1.1.dist-info/top_level.txt
cmp_text_files-0.1.1.dist-info/RECORD
