Metadata-Version: 2.1
Name: cmp-text-files
Version: 0.1.1
Summary: Library for compare text files
Home-page: https://cmp_text_files.readthedocs.io/
Author: Mukhammaddiyor Khaydaraliev
Author-email: haydaraliyevmd@gmail.com
License: None
Platform: UNKNOWN
Classifier: Intended Audience :: Developers
Classifier: Programming Language :: Python
Classifier: Programming Language :: Python :: 3
Classifier: Programming Language :: Python :: 3.6
Classifier: Programming Language :: Python :: 3.7
Classifier: Programming Language :: Python :: 3.8
Classifier: Programming Language :: Python :: 3.9
Classifier: Operating System :: OS Independent
Requires-Dist: difflib
